accelbyte_py_sdk/api/iam/__init__.py
accelbyte_py_sdk/api/iam/errors.py
accelbyte_py_sdk/api/iam/models/__init__.py
accelbyte_py_sdk/api/iam/models/account_create_test_user_request_v4.py
accelbyte_py_sdk/api/iam/models/account_create_test_user_response_v4.py
accelbyte_py_sdk/api/iam/models/account_create_test_users_request_v4.py
accelbyte_py_sdk/api/iam/models/account_create_test_users_response_v4.py
accelbyte_py_sdk/api/iam/models/account_create_user_request_v4.py
accelbyte_py_sdk/api/iam/models/account_create_user_response_v4.py
accelbyte_py_sdk/api/iam/models/account_upgrade_headless_account_request_v4.py
accelbyte_py_sdk/api/iam/models/account_upgrade_headless_account_with_verification_code_forward_request_v4.py
accelbyte_py_sdk/api/iam/models/account_upgrade_headless_account_with_verification_code_request_v4.py
accelbyte_py_sdk/api/iam/models/account_user_active_ban_response_v4.py
accelbyte_py_sdk/api/iam/models/account_user_info.py
accelbyte_py_sdk/api/iam/models/account_user_permissions_response_v4.py
accelbyte_py_sdk/api/iam/models/account_user_response_v4.py
accelbyte_py_sdk/api/iam/models/accountcommon_allowed_permission.py
accelbyte_py_sdk/api/iam/models/accountcommon_avatar_config.py
accelbyte_py_sdk/api/iam/models/accountcommon_ban.py
accelbyte_py_sdk/api/iam/models/accountcommon_ban_reason.py
accelbyte_py_sdk/api/iam/models/accountcommon_ban_reason_v3.py
accelbyte_py_sdk/api/iam/models/accountcommon_ban_reasons.py
accelbyte_py_sdk/api/iam/models/accountcommon_ban_reasons_v3.py
accelbyte_py_sdk/api/iam/models/accountcommon_ban_v3.py
accelbyte_py_sdk/api/iam/models/accountcommon_banned_by_v3.py
accelbyte_py_sdk/api/iam/models/accountcommon_bans.py
accelbyte_py_sdk/api/iam/models/accountcommon_bans_v3.py
accelbyte_py_sdk/api/iam/models/accountcommon_client_module_permission.py
accelbyte_py_sdk/api/iam/models/accountcommon_client_permission.py
accelbyte_py_sdk/api/iam/models/accountcommon_client_permission_set.py
accelbyte_py_sdk_service_iam-0.28.0.dist-info/METADATA
accelbyte_py_sdk_service_iam-0.28.0.dist-info/WHEEL
accelbyte_py_sdk_service_iam-0.28.0.dist-info/top_level.txt
accelbyte_py_sdk_service_iam-0.28.0.dist-info/RECORD
