Metadata-Version: 2.4
Name: accelbyte-py-sdk-service-iam
Version: 0.28.0
Summary: AccelByte Python SDK - AccelByte Gaming Services Iam Service
Requires-Python: >=3.9
Requires-Dist: accelbyte-py-sdk-core
